spanish_chat_sdk/__init__.py
spanish_chat_sdk/api/__init__.py
spanish_chat_sdk/api/chat/__init__.py
spanish_chat_sdk/api/chat/get_placement_test_chat_get_placement_test_get.py
spanish_chat_sdk/api/chat/send_message_chat_send_message_post.py
spanish_chat_sdk/api/conversations/__init__.py
spanish_chat_sdk/api/conversations/end_all_user_conversations_conversations_end_all_get.py
spanish_chat_sdk/api/conversations/end_conversation_conversations_end_post.py
spanish_chat_sdk/api/conversations/get_current_conversation_messages_conversations_active_messages_post.py
spanish_chat_sdk/api/conversations/start_conversation_conversations_start_post.py
spanish_chat_sdk/api/default/__init__.py
spanish_chat_sdk/api/default/welcome_get.py
spanish_chat_sdk/api/grammar/__init__.py
spanish_chat_sdk/api/grammar/check_grammar_grammar_check_post.py
spanish_chat_sdk/api/grammar/check_grammar_v2_grammar_check_v2_post.py
spanish_chat_sdk/api/grammar/translate_message_grammar_translate_post.py
spanish_chat_sdk/api/users/__init__.py
spanish_chat_sdk/api/users/get_current_cefr_level_users_cefr_level_get.py
spanish_chat_sdk/api/users/get_me_users_me_get.py
spanish_chat_sdk/api/users/get_users_users_get.py
spanish_chat_sdk/api/users/login_for_access_token_users_token_post.py
spanish_chat_sdk/api/users/register_account_users_register_post.py
spanish_chat_sdk/client.py
spanish_chat_sdk/errors.py
spanish_chat_sdk/models/__init__.py
spanish_chat_sdk/models/body_login_for_access_token_users_token_post.py
spanish_chat_sdk/models/conversation.py
spanish_chat_sdk/models/grammar_error.py
spanish_chat_sdk/models/grammar_error_v2.py
spanish_chat_sdk/models/grammar_errors.py
spanish_chat_sdk/models/grammar_errors_v2.py
spanish_chat_sdk/models/http_validation_error.py
spanish_chat_sdk/models/message.py
spanish_chat_sdk/models/placement_test_answer.py
spanish_chat_sdk/models/placement_test_follow_up_question.py
spanish_chat_sdk/models/placement_test_question.py
spanish_chat_sdk-0.1.9.dist-info/METADATA
spanish_chat_sdk-0.1.9.dist-info/WHEEL
spanish_chat_sdk-0.1.9.dist-info/RECORD
